kdot/__init__.py
kdot-0.0.3.dist-info/LICENSE
kdot-0.0.3.dist-info/METADATA
kdot-0.0.3.dist-info/WHEEL
kdot-0.0.3.dist-info/top_level.txt
kdot-0.0.3.dist-info/RECORD
