Metadata-Version: 2.1
Name: kdot
Version: 0.0.3
Summary: A anti skid package
Author: kdot227
Author-email: suckmaballs@gmail.com
License: MIT
Keywords: kdot
Classifier: Development Status :: 3 - Alpha
Classifier: Intended Audience :: Developers
Classifier: License :: OSI Approved :: MIT License
Classifier: Programming Language :: Python :: 3
License-File: LICENSE
